tls_client/__init__.py
tls_client/__version__.py
tls_client/cffi.py
tls_client/cookies.py
tls_client/exceptions.py
tls_client/response.py
tls_client/sessions.py
tls_client/settings.py
tls_client/structures.py
tls_client/update_shared_libraries.py
tls_client/utils.py
tls_client/async_client/__init__.py
tls_client/async_client/sessions.py
tls_client/dependencies/__init__.py
tls_client/dependencies/tls-client-32.dll
tls_client/dependencies/tls-client-64.dll
tls_client/dependencies/tls-client-amd64.so
tls_client/dependencies/tls-client-arm64.dylib
tls_client/dependencies/tls-client-arm64.so
tls_client/dependencies/tls-client-x86.dylib
tls_client/dependencies/tls-client-x86.so
999tls_client-1.0.5.dist-info/LICENSE
999tls_client-1.0.5.dist-info/METADATA
999tls_client-1.0.5.dist-info/WHEEL
999tls_client-1.0.5.dist-info/top_level.txt
999tls_client-1.0.5.dist-info/RECORD
